django_sae/__init__.py
django_sae/auth/__init__.py
django_sae/auth/backends.py
django_sae/models/__init__.py
django_sae/models/base.py
django_sae/models/session.py
django_sae/models/user.py
django_sae/session/__init__.py
django_sae/session/backends/__init__.py
django_sae/session/backends/db.py
django_saengine-0.0.4.dist-info/DESCRIPTION.rst
django_saengine-0.0.4.dist-info/METADATA
django_saengine-0.0.4.dist-info/RECORD
django_saengine-0.0.4.dist-info/WHEEL
django_saengine-0.0.4.dist-info/metadata.json
django_saengine-0.0.4.dist-info/top_level.txt
