Metadata-Version: 2.0
Name: django-saengine
Version: 0.0.4
Summary: django session auth engine
Home-page: http://www.hshl.ltd
Author: bigtiger
Author-email: chinafengheping@gmail.com
License: UNKNOWN
Platform: UNKNOWN
Requires-Dist: django (>=1.7.7)
Requires-Dist: django-restful (>=0.0.4)
Requires-Dist: requests (>=2.18.4)
Requires-Dist: six
